Metadata-Version: 1.0
Name: textaugH
Version: 0.2.4
Summary: Little package for text augmentation
Home-page: https://github.com/comptechaug/textaug
Author: TextAugmentationTeam
Author-email: comptechaugteam@gmail.com
License: MIT
Platform: UNKNOWN
